setup.py
nlptool/__init__.py
nlptool/distance.py
nlptool/pinyin.py
nlptool/simhash.py
nlptool/test.py
nlptool.egg-info/PKG-INFO
nlptool.egg-info/SOURCES.txt
nlptool.egg-info/dependency_links.txt
nlptool.egg-info/requires.txt
nlptool.egg-info/top_level.txt