Metadata-Version: 1.0
Name: nlptool
Version: 0.0.2
Summary: nlptool (just for test))
Home-page: UNKNOWN
Author: darrenwang
Author-email: darrenwang00@163.com
License: MIT License
Keywords: nlp,tool
Platform: any
